{
  "content": [
    {
      "type": "paragraph",
      "children": [
        {
          "text": ""
        }
      ]
    },
    {
      "type": "grid",
      "layout": [
        2,
        4
      ],
      "children": [
        {
          "type": "column",
          "children": [
            {
              "type": "paragraph",
              "children": [
                {
                  "text": "NBAP with AVAnnotate",
                  "textSize": "heading-one"
                }
              ]
            }
          ]
        }
      ]
    },
    {
      "type": "paragraph",
      "children": [
        {
          "text": ""
        }
      ]
    },
    {
      "type": "grid",
      "layout": [
        2,
        4
      ],
      "children": [
        {
          "type": "column",
          "children": [
            {
              "type": "paragraph",
              "children": [
                {
                  "text": ""
                }
              ]
            },
            {
              "type": "image",
              "url": "https://noboundariesarchive.com/media/collectiveaccess/images/7/60324_ca_object_representations_media_717_mediumlarge.jpg",
              "caption": "Program from No Boundaries 2018",
              "children": [
                {
                  "text": ""
                }
              ]
            },
            {
              "type": "paragraph",
              "children": [
                {
                  "textSize": "small",
                  "text": "Program from No Boundaries 2018",
                  "link": "https://noboundariesarchive.com/Detail/objects/654"
                }
              ]
            }
          ]
        },
        {
          "type": "column",
          "children": [
            {
              "type": "paragraph",
              "children": [
                {
                  "text": "A collection of audiovisual artifacts from the "
                },
                {
                  "text": "No Boundaries Archive Project (NBAP) ",
                  "bold": true
                },
                {
                  "text": "with annotations to make the artifacts more easily searchable and discoverable. "
                }
              ]
            },
            {
              "type": "paragraph",
              "children": [
                {
                  "text": ""
                }
              ]
            },
            {
              "type": "paragraph",
              "children": [
                {
                  "text": "With this project, we hope to unlock new ways of interacting with and experiencing dance as performance, expression, and meaning."
                }
              ]
            },
            {
              "type": "paragraph",
              "children": [
                {
                  "text": ""
                }
              ]
            },
            {
              "type": "paragraph",
              "children": [
                {
                  "text": "Visit the "
                },
                {
                  "text": "No Boundaries Archive Project ",
                  "link": "https://noboundariesarchive.com/"
                },
                {
                  "text": "to learn more!"
                }
              ]
            }
          ]
        }
      ]
    },
    {
      "type": "paragraph",
      "children": [
        {
          "text": ""
        }
      ]
    },
    {
      "type": "table-of-contents",
      "children": [
        {
          "text": ""
        }
      ]
    },
    {
      "type": "paragraph",
      "children": [
        {
          "text": ""
        }
      ]
    },
    {
      "type": "paragraph",
      "children": [
        {
          "text": ""
        }
      ]
    },
    {
      "type": "paragraph",
      "children": [
        {
          "text": ""
        }
      ]
    },
    {
      "type": "paragraph",
      "children": [
        {
          "text": "\n"
        }
      ]
    }
  ],
  "created_at": "2025-10-05T19:49:11.445Z",
  "created_by": "DataMuseology",
  "title": "NBAP with AVAnnotate",
  "updated_at": "2026-04-19T20:12:26.236Z",
  "updated_by": "DataMuseology",
  "autogenerate": {
    "enabled": false,
    "type": "home"
  },
  "slug": "nbap-with-avannotate"
}